beancount_gocardless/__init__.py
beancount_gocardless/cli.py
beancount_gocardless/client.py
beancount_gocardless/importer.py
beancount_gocardless/models.py
beancount_gocardless/tui.py
beancount_gocardless/openapi/swagger.json
beancount_gocardless-0.1.13.dist-info/METADATA
beancount_gocardless-0.1.13.dist-info/WHEEL
beancount_gocardless-0.1.13.dist-info/entry_points.txt
beancount_gocardless-0.1.13.dist-info/licenses/LICENSE
beancount_gocardless-0.1.13.dist-info/RECORD
