Metadata-Version: 2.4
Name: beancount-gocardless
Version: 0.1.13
License-Expression: Unlicense
License-File: LICENSE
Requires-Python: <4,>=3.12
Requires-Dist: beancount
Requires-Dist: beangulp
Requires-Dist: pre-commit>=4.5.1
Requires-Dist: pydantic>=2.0.0
Requires-Dist: pyyaml
Requires-Dist: requests
Requires-Dist: requests-cache
Requires-Dist: rich
Requires-Dist: textual-dev>=1.7.0
Requires-Dist: textual>=3.2.0
Provides-Extra: dev
Requires-Dist: myst-parser; extra == 'dev'
Requires-Dist: sphinx; extra == 'dev'
Requires-Dist: sphinx-rtd-theme; extra == 'dev'
Provides-Extra: lint
Requires-Dist: ruff>=0.9.8; extra == 'lint'
Provides-Extra: test
Requires-Dist: pytest; extra == 'test'
Requires-Dist: pytest-asyncio; extra == 'test'
